MANIFEST.in
README.md
setup.py
p4a_radiant.egg-info/PKG-INFO
p4a_radiant.egg-info/SOURCES.txt
p4a_radiant.egg-info/dependency_links.txt
p4a_radiant.egg-info/top_level.txt
radiant/__init__.py
radiant/framework/__init__.py
radiant/framework/shortcuts.py
radiant/framework/theme.py
radiant/framework/urls.py
radiant/framework/views.py
radiant/framework/brython/__init__.py
radiant/framework/brython/exporter.py
radiant/framework/brython/permissions.py
radiant/framework/brython/settings.py
radiant/framework/brython/static_views.py
radiant/framework/brython/urls.py
radiant/framework/brython/views.py
radiant/framework/brython/wsgi.py
radiant/framework/templates/radiant/brython.html
radiant/framework/templates/radiant/brython_mdc.html
radiant/framework/templates/radiant/logs.html
radiant/framework/templates/radiant/mdc.html
radiant/framework/templates/radiant/brythonframework/base.html
radiant/framework/templates/radiant/brythonframework/export.html
radiant/framework/templatetags/__init__.py
radiant/framework/templatetags/custom_include.py