Metadata-Version: 1.2
Name: p4a-radiant
Version: 2.4
Summary: A Python Framework for Android Apps Development.
Home-page: http://yeisoncardona.com/
Author: Yeison Cardona
Author-email: yeisoneng@gmail.com
Maintainer: Yeison Cardona
Maintainer-email: yeisoneng@gmail.com
License: BSD License
Download-URL: https://bitbucket.org/radiantforandroid/radiantframework/downloads/
Platform: UNKNOWN
Classifier: Environment :: Web Environment
Classifier: Framework :: Django
